h3_pyspark/__init__.py
h3_pyspark/indexing.py
h3_pyspark/traversal.py
h3_pyspark/utils.py
h3_pyspark-1.2.6.dist-info/LICENSE
h3_pyspark-1.2.6.dist-info/METADATA
h3_pyspark-1.2.6.dist-info/WHEEL
h3_pyspark-1.2.6.dist-info/top_level.txt
h3_pyspark-1.2.6.dist-info/RECORD
