Metadata-Version: 2.1
Name: h3-pyspark
Version: 1.2.6
Summary: PySpark bindings for H3, a hierarchical hexagonal geospatial indexing system
Home-page: https://github.com/kevinschaich/h3-pyspark
Author: Kevin Schaich
Author-email: schaich.kevin@gmail.com
License: UNKNOWN
Project-URL: Bug Tracker, https://github.com/kevinschaich/h3-pyspark/issues
Platform: UNKNOWN
Classifier: Programming Language :: Python :: 3
Classifier: License :: OSI Approved :: MIT License
Classifier: Operating System :: OS Independent
Requires-Python: >=3.6
License-File: LICENSE
